django_zipfile/__init__.py
django_zipfile/models.py
django_zipfile/templatezipfile.py
django_zipfile-0.4.0.dist-info/METADATA
django_zipfile-0.4.0.dist-info/RECORD
django_zipfile-0.4.0.dist-info/WHEEL
django_zipfile-0.4.0.dist-info/top_level.txt
