Metadata-Version: 1.1
Name: django-zipfile
Version: 0.4.0
Summary: A ZipFile subclass that accepts Django Templates
Home-page: https://github.com/fcurella/django-zipfile
Author: Flavio Curella
Author-email: flavio.curella@gmail.com
License: MIT
Platform: UNKNOWN
Classifier: Development Status :: 4 - Beta
Classifier: Environment :: Console
Classifier: Intended Audience :: Developers
Classifier: Intended Audience :: Information Technology
Classifier: License :: OSI Approved :: MIT License
Classifier: Operating System :: OS Independent
Classifier: Programming Language :: Python
Classifier: Framework :: Django
